netsim/__init__.py
netsim-0.0.0.dist-info/METADATA
netsim-0.0.0.dist-info/WHEEL
netsim-0.0.0.dist-info/top_level.txt
netsim-0.0.0.dist-info/RECORD
