Metadata-Version: 2.1
Name: netsim
Version: 0.0.0
Summary: Network simulation
Home-page: UNKNOWN
Author: Marcos Llobera
Author-email: UNKNOWN
License: UNKNOWN
Platform: UNKNOWN
Classifier: Development Status :: 1 - Planning
